Metadata-Version: 2.1
Name: singular-launcher
Version: 1.0.1
Summary: Singular API For Launching Experiments Using Singularity On Slurm
Home-page: https://github.com/brandontrabucco/singular
Author: Brandon Trabucco
Author-email: brandon@btrabucco.com
License: MIT
Download-URL: https://github.com/brandontrabucco/singular/archive/v1_0_1.tar.gz
Keywords: Deep Learning,Research,Management
Platform: UNKNOWN
Classifier: Intended Audience :: Developers
Classifier: Intended Audience :: Science/Research
Classifier: Topic :: Scientific/Engineering
Classifier: Topic :: Scientific/Engineering :: Artificial Intelligence
Classifier: Topic :: Scientific/Engineering :: Mathematics
Classifier: Topic :: Software Development
Classifier: Topic :: Software Development :: Libraries
Classifier: Topic :: Software Development :: Libraries :: Python Modules
Classifier: License :: OSI Approved :: MIT License
Classifier: Programming Language :: Python :: 3
Classifier: Programming Language :: Python :: 3.7
Classifier: Programming Language :: Python :: 3.8
License-File: LICENSE
